DXR_BJ/__init__.py
DXR_BJ/drawer.py
DXR_BJ/common/dependency/alg_name.yaml
DXR_BJ/common/dependency/simsun.ttc
DXR_BJ-1.1.3.dist-info/METADATA
DXR_BJ-1.1.3.dist-info/WHEEL
DXR_BJ-1.1.3.dist-info/top_level.txt
DXR_BJ-1.1.3.dist-info/RECORD
